pydis/__init__.py
pydis/core.py
pydis/exceptions.py
pydis/utils.py
pydis/value.py
pydis/version.py
test/__init__.py
test/test_core.py
pydictdis-0.1.5.dist-info/LICENSE
pydictdis-0.1.5.dist-info/METADATA
pydictdis-0.1.5.dist-info/WHEEL
pydictdis-0.1.5.dist-info/top_level.txt
pydictdis-0.1.5.dist-info/RECORD
