Metadata-Version: 2.1
Name: pydictdis
Version: 0.1.5
Summary: Management similar to redis interface
Home-page: https://github.com/Zombie123456/pydis
Author: chalice
Author-email: lichangyin888@gmail.com
Requires-Python: >=3.6
License-File: LICENSE
